escapetheforest/__init__.py
escapetheforest/__main__.py
escapetheforest/actions.py
escapetheforest/enemies.py
escapetheforest/items.py
escapetheforest/map.txt
escapetheforest/player.py
escapetheforest/tiles.py
escapetheforest/world.py
escapetheforest-0.2.6.dist-info/LICENSE
escapetheforest-0.2.6.dist-info/METADATA
escapetheforest-0.2.6.dist-info/WHEEL
escapetheforest-0.2.6.dist-info/top_level.txt
escapetheforest-0.2.6.dist-info/RECORD
