Metadata-Version: 2.1
Name: escapetheforest
Version: 0.2.6
Summary: A small adventure game. Escape a forest full of ill-intended creatures!
Home-page: https://github.com/pypa/sampleproject
Author: Tom
Author-email: albin.tveitan@gmail.com
License: UNKNOWN
Platform: UNKNOWN
Classifier: Programming Language :: Python :: 3
Classifier: License :: OSI Approved :: MIT License
Classifier: Operating System :: OS Independent
Requires-Python: >=3.6
